{
  "personal": {
    "name": "Aditya Saktyawan Widhiantara",
    "phone": "+6281235916971",
    "email": "adityaswidhiantara@gmail.com",
    "linkedin": "https://linkedin.com/in/aditya-s-widhiantara",
    "github": "https://github.com/adith-widhiantara"
  },
  "objective": "Software Engineer and Open-Source Creator with deep expertise in architecting high-performance enterprise systems. Proven track record in optimizing high-concurrency platforms using proprietary frameworks, asynchronous patterns, and strict coding standards to deliver reliable mission-critical solutions. Passionate about engineering excellence, mentoring teams to reduce technical debt, and driving innovation through scalable software architecture that supports sustained business growth.",
  "experiences": [
    {
      "id": "exp-001",
      "title": "Software Engineer",
      "company": "PT Sentra Vidya Utama",
      "period": {
        "start": "2025-12",
        "end": null,
        "current": true
      },
      "highlights": [
        "Architected high-performance systems using proprietary framework and Memcached",
        "Decoupled background processes via RabbitMQ to optimize performance",
        "Developed robust, strictly typed REST APIs adhering to SOLID principles to ensure reliable and seamless system integration"
      ],
      "techStack": ["PHP", "Proprietary Framework", "Laravel", "PostgreSQL", "Memcached", "RabbitMQ"],
      "practices": ["REST API", "SOLID", "System Architecture"]
    },
    {
      "id": "exp-002",
      "title": "Software Engineer",
      "company": "PT Javan Cipta Solusi",
      "period": {
        "start": "2025-07",
        "end": "2025-12",
        "current": false
      },
      "highlights": [
        "Designing and Developing Scalable System Architectures",
        "Developing High-Quality Code and Conducting Code Reviews",
        "Collaborating with Cross-Functional Teams and Providing Innovative Solutions"
      ],
      "techStack": ["PHP", "Laravel 10", "JavaScript", "React.js", "Java", "Spring Camunda"],
      "practices": ["REST API", "SOLID", "Agile/Scrum", "Camunda BPM"]
    },
    {
      "id": "exp-003",
      "title": "Product Owner",
      "company": "PT Javan Cipta Solusi",
      "period": {
        "start": "2024-11",
        "end": "2025-07",
        "current": false
      },
      "highlights": [
        "Defined technical requirements and translated them into clear and actionable documentation",
        "Planned and led sprint activities while maintaining consistent client communication",
        "Coordinated task assignments to ensure timely delivery and compliance with project standards"
      ],
      "techStack": ["Metabase", "Office 365"],
      "practices": ["SDLC", "Agile/Scrum"]
    },
    {
      "id": "exp-004",
      "title": "Full Stack Developer",
      "company": "PT Javan Cipta Solusi",
      "period": {
        "start": "2023-08",
        "end": "2024-11",
        "current": false
      },
      "highlights": [
        "Developed modular features to reduce cognitive complexity and enhance maintainability",
        "Integrated caching strategies that significantly boosted system response time",
        "Authored comprehensive technical documentation to support knowledge transfer and onboarding"
      ],
      "techStack": ["PHP", "Laravel 10", "JavaScript", "React.js", "Java", "Spring Camunda"],
      "practices": ["REST API", "SOLID", "Agile/Scrum", "Camunda BPM"]
    },
    {
      "id": "exp-005",
      "title": "Full Stack Developer",
      "company": "PT Aku Bisa Ibadah",
      "period": {
        "start": "2024-05",
        "end": "2024-11",
        "current": false
      },
      "highlights": [
        "Developed modular features to reduce cognitive complexity and enhance maintainability",
        "Integrated caching strategies that significantly boosted system response time",
        "Authored comprehensive technical documentation to support knowledge transfer and onboarding"
      ],
      "techStack": ["PHP", "Laravel 10", "JavaScript", "React.js", "Java", "Spring Camunda"],
      "practices": ["REST API", "SOLID", "Agile/Scrum"]
    },
    {
      "id": "exp-006",
      "title": "Project Management Officer",
      "company": "PT Indah Karya (Persero)",
      "period": {
        "start": "2023-01",
        "end": "2023-08",
        "current": false
      },
      "highlights": [
        "Monitored project KPIs and generated performance reports for early issue detection",
        "Established standardized procedures to optimize project workflows",
        "Maintained project documentation and ensured accurate version control"
      ],
      "techStack": ["Office 365"],
      "practices": []
    },
    {
      "id": "exp-007",
      "title": "Full Stack Developer",
      "company": "PT Indah Karya (Persero)",
      "period": {
        "start": "2022-08",
        "end": "2023-08",
        "current": false
      },
      "highlights": [
        "Developed a tender monitoring platform integrated with the Indonesian LPSE system",
        "Created a real-time project monitoring system to support transparency and accountability",
        "Built a secure digital signature application for seamless e-signature generation"
      ],
      "techStack": ["PHP", "Laravel 10"],
      "practices": ["REST API", "SOLID", "SDLC"]
    },
    {
      "id": "exp-008",
      "title": "Backend & Full Stack Developer",
      "company": "PT Hashmicro Solusi Indonesia",
      "period": {
        "start": "2021-07",
        "end": "2023-08",
        "current": false
      },
      "highlights": [
        "Build, and maintain some application with SaaS Technology and RESTful API",
        "Maintain, and improve website performance in terms of speed, security, user convenience, and others",
        "Optimized SQL queries for the heavy-load parts of the system which improved website responsiveness"
      ],
      "techStack": ["PHP", "Laravel 8"],
      "practices": ["REST API", "SOLID", "SDLC"]
    },
    {
      "id": "exp-009",
      "title": "Chief Technology Officer",
      "company": "PT Tradeco Indonesia Karya",
      "period": {
        "start": "2021-03",
        "end": "2022-08",
        "current": false
      },
      "highlights": [
        "Assist, design, and establish technical policies and producing the technical components of the strategic planning process",
        "Design, and develop a website application to show our product to worldwide users utilizing Laravel 8 Framework",
        "Ensure that the products marketed through the website have passed the Google SEO criteria",
        "Maintain and improve website performance in terms of speed, security, user convenience, and others"
      ],
      "techStack": ["PHP", "Laravel 8"],
      "practices": ["REST API", "SOLID", "SDLC"]
    },
    {
      "id": "exp-010",
      "title": "Full Stack Developer",
      "company": "Freelance",
      "period": {
        "start": "2021-03",
        "end": "2022-08",
        "current": false
      },
      "highlights": [
        "Used various technologies, including JavaScript to make code repairs and optimize corporate website",
        "Determined coding requirements for site creation, including e-commerce capability and security",
        "Tested websites and performed user testing and troubleshooting prior to live deployment",
        "Analysed requirements and designed, developed and implemented software applications for multiple websites"
      ],
      "techStack": ["PHP", "Laravel 7", "Laravel 8", "JavaScript"],
      "practices": ["REST API", "SOLID", "SDLC"]
    },
    {
      "id": "exp-011",
      "title": "Backend Developer",
      "company": "Travens",
      "period": {
        "start": "2021-03",
        "end": "2021-07",
        "current": false
      },
      "highlights": [
        "Responsible for defining, developing, and evolving software in a fast paced and agile development environment",
        "Responsible to build RESTful API"
      ],
      "techStack": ["PHP", "Laravel 7"],
      "practices": ["REST API", "SOLID", "SDLC"]
    },
    {
      "id": "exp-012",
      "title": "Chief Coordinator & Lecturer Assistant",
      "company": "Geographic Information System Laboratory, Faculty of Computer Science, Jember University",
      "period": {
        "start": "2018-09",
        "end": "2020-08",
        "current": false
      },
      "highlights": [
        "Lead, and coordinate all laboratory activities",
        "Monitor the utilization of existing facilities and infrastructure in the laboratory",
        "Provide an evaluation of the performance results of laboratory members",
        "Coordinate with related lecturers"
      ],
      "techStack": [],
      "practices": []
    },
    {
      "id": "exp-013",
      "title": "Lecturer Assistant",
      "company": "Networking Laboratory, Faculty of Computer Science, Jember University",
      "period": {
        "start": "2018-09",
        "end": "2020-08",
        "current": false
      },
      "highlights": [
        "Help students to understand the course by live practice",
        "Assesses student's assignment"
      ],
      "techStack": [],
      "practices": []
    },
    {
      "id": "exp-014",
      "title": "Frontend Developer",
      "company": "Annas Florist",
      "period": {
        "start": "2020-01",
        "end": "2020-03",
        "current": false
      },
      "highlights": [
        "Built mock up designs, and wireframes for landing, and e-commerce page",
        "Develop frontend page with modern blade template, HTML, and JavaScript"
      ],
      "techStack": ["PHP", "HTML", "JavaScript"],
      "practices": []
    }
  ],
  "education": [
    {
      "id": "edu-001",
      "institution": "Jember University",
      "location": "East Java, Indonesia",
      "degree": "Bachelor's degree in Information Systems",
      "faculty": "Faculty of Computer Science",
      "period": {
        "start": "2017-06",
        "end": "2021-06"
      },
      "finalProject": "Conducted research paper on developing website-based integrated village administration systems using Prototype SDLC and UCD Method",
      "techStack": ["PHP", "Laravel 8"],
      "practices": ["REST API", "SOLID", "SDLC"]
    }
  ],
  "skills": {
    "backend": [
      {
        "name": "PHP (Laravel)",
        "highlights": [
          "Rapid development using MVC structure and Artisan CLI",
          "Built-in tools for authentication, caching, queues, and testing",
          "Elegant syntax for clean, maintainable code",
          "Ensured ≥ 90% unit-test coverage with PHPUnit"
        ]
      },
      {
        "name": "Java (Spring Camunda)",
        "highlights": [
          "Scalable & robust architecture for high-load enterprise applications",
          "Integrated workflow engine simplifies business process orchestration",
          "Extensive ecosystem with rich libraries and strong community support",
          "Achieved ≥ 90% unit-test coverage using JUnit and Mockito"
        ]
      }
    ],
    "frontend": [
      {
        "name": "React.js",
        "highlights": [
          "Reusable components for faster development and consistent UI",
          "Virtual DOM ensures high-performance rendering",
          "Vast ecosystem of community-driven packages",
          "Maintained ≥ 90% unit-test coverage using Jest & React Testing Library"
        ]
      },
      {
        "name": "Next.js",
        "highlights": [
          "Server-side rendering (SSR) and static-site generation (SSG) for optimal SEO and load times",
          "File-based routing for automatic route creation",
          "Full integration with React, including API routes and image optimization",
          "Secured ≥ 90% unit-test coverage via Jest & React Testing Library"
        ]
      },
      {
        "name": "jQuery",
        "highlights": [
          "Simple DOM manipulation and concise AJAX calls",
          "Broad browser compatibility without extra configuration",
          "Lightweight and easy to learn for quick UI enhancements"
        ]
      }
    ],
    "databases": ["PostgreSQL", "MySQL", "MariaDB"],
    "practices": ["RESTful API", "SOLID principles", "Agile development (Scrum)"],
    "cachingAndMessaging": ["Redis", "Memcached", "RabbitMQ"],
    "tools": ["Git", "Docker", "Metabase", "Office 365", "Camunda Modeler"]
  },
  "certifications": [
    {
      "category": "Programming & Database",
      "items": [
        { "name": "Administrating Database", "issuer": "Indonesian Professional Certification Authority" },
        { "name": "Programming", "issuer": "Indonesian Professional Certification Authority" }
      ]
    },
    {
      "category": "HackerRank",
      "items": [
        { "name": "SQL Certificate", "issuer": "HackerRank" },
        { "name": "Rest API - Intermediate", "issuer": "HackerRank" },
        { "name": "Problem Solving Certificate - Intermediate", "issuer": "HackerRank" },
        { "name": "Problem Solving Certificate - Basic", "issuer": "HackerRank" }
      ]
    },
    {
      "category": "Other",
      "items": [
        { "name": "Progate Certificate", "issuer": "Progate" }
      ]
    }
  ],
  "openSource": [
    {
      "id": "os-001",
      "name": "Laravel Async Audit Logger",
      "role": "Creator & Maintainer",
      "url": "https://github.com/adith-widhiantara/laravel-async-audit-logger",
      "description": "This package provides an asynchronous audit logging system using Redis as a buffer and a Daemon Worker for bulk database insertion. It is designed to handle high-traffic applications where traditional synchronous logging would cause performance bottlenecks."
    },
    {
      "id": "os-002",
      "name": "Laravel Advanced CRUD Generator",
      "role": "Creator & Maintainer",
      "url": "https://github.com/adith-widhiantara/crud",
      "description": "Designed a modular Laravel package utilizing the Service-Repository Pattern to automate backend scaffolding via custom Artisan commands, implementing Metaprogramming and Reflection API for dynamic database schema validation. The solution features an abstract filtering and sorting engine optimized to handle complex nested relationship searches without N+1 query issues, while ensuring data integrity through atomic bulk operations secured by database transactions."
    }
  ],
  "projects": [
    {
      "id": "proj-001",
      "name": "SiakadCloud Product",
      "company": "PT Sentra Vidya Utama",
      "description": "Developed a comprehensive cloud-based academic information system for universities, integrating modules for student management, course scheduling, and faculty administration. Implemented a robust backend architecture to support high concurrency and ensure data integrity across multiple campuses.",
      "techStack": ["PHP", "RabbitMQ"]
    },
    {
      "id": "proj-002",
      "name": "E-Sign V2 Platform",
      "company": "PT Sentra Vidya Utama",
      "description": "Engineered the core backend infrastructure for the centralized E-Sign platform, specifically designing a high-throughput logging system to trace complex vendor integrations and ensure strict audit compliance. Simultaneously developed an asynchronous event-driven notification service utilizing RabbitMQ to decouple email and in-system alerts from main processes.",
      "techStack": ["PHP", "RabbitMQ"]
    },
    {
      "id": "proj-003",
      "name": "WhatsApp Blasting Tool",
      "company": "PT Javan Cipta Solusi",
      "description": "Development of an internal application for broadcasting WhatsApp messages. The tool is designed with features for comprehensive customer data management and flexible message content management, with the ability to schedule and execute message delivery.",
      "techStack": ["PHP", "Laravel"]
    },
    {
      "id": "proj-004",
      "name": "Internal QA Tools",
      "company": "PT Javan Cipta Solusi",
      "description": "Development of a specialized internal tool for the Quality Assurance team. A centralized platform that streamlines and manages various aspects of the QA workflow including test cases, issue tracking, software releases, and test runs.",
      "techStack": ["PHP", "Laravel"]
    },
    {
      "id": "proj-005",
      "name": "Anti-Corruption Complaint Handling System",
      "company": "PT Javan Cipta Solusi & Komisi Pemberantasan Korupsi RI",
      "description": "Maintenance of the KPK-KWS 2023 application and its supporting systems, used for managing public complaints related to corruption cases. Ensured system stability and performance to support effective case handling by the authorities.",
      "techStack": ["PHP", "Laravel"]
    },
    {
      "id": "proj-006",
      "name": "Ops Console Enhancements",
      "company": "PT Javan Cipta Solusi & PT Bank Rakyat Indonesia Tbk",
      "description": "Enhancement of BRI's Ops Console system, focusing on the Manual Reconciliation module and the RTGS (Real-Time Gross Settlement) module. Delivered strategic dashboards to support executive decision-making.",
      "techStack": ["PHP", "Laravel", "Java", "Spring Camunda"]
    },
    {
      "id": "proj-007",
      "name": "Internal Data Validation Platform for Telco Integration",
      "company": "PT Javan Cipta Solusi, PT Linknet & PT XL Axiata",
      "description": "Developed the Interval System for PT Linknet, designed to validate HPDB data prior to submission to PT XL Axiata's LMS application. Streamlined data submission processes and significantly improved operational efficiency.",
      "techStack": ["PHP", "Laravel"]
    },
    {
      "id": "proj-008",
      "name": "HRM Implementation",
      "company": "PT Javan Cipta Solusi & CV Kunikita Persada",
      "description": "Led the implementation of an HRM module fully integrated with Odoo ERP to automate and optimize employee monitoring. Enabled real-time synchronization of attendance, leave, and payroll data.",
      "techStack": ["PHP", "Laravel", "Odoo ERP"]
    },
    {
      "id": "proj-009",
      "name": "LPSE Monitoring",
      "company": "PT Indah Karya (Persero)",
      "description": "Developed a comprehensive platform to track tender projects across more than 50 LPSE websites, providing real-time updates and insights based on specific project criteria.",
      "techStack": ["PHP", "Laravel"]
    },
    {
      "id": "proj-010",
      "name": "Project Monitoring",
      "company": "PT Indah Karya (Persero)",
      "description": "Designed and implemented a robust system to monitor the progress of ongoing projects at PT Indah Karya, covering both physical and financial aspects with real-time status updates.",
      "techStack": ["PHP", "Laravel"]
    },
    {
      "id": "proj-011",
      "name": "Link Shortener",
      "company": "PT Indah Karya (Persero)",
      "description": "Developed a secure and efficient URL shortening tool to streamline the sharing of official links, improving the credibility of links shared by PT Indah Karya.",
      "techStack": ["PHP", "Laravel"]
    },
    {
      "id": "proj-012",
      "name": "Bank Integration",
      "company": "PT Hashmicro",
      "description": "Created a dynamic website that integrates various banking services into a unified platform enabling intra-bank and inter-bank transfers, mutation checks, virtual account payments, and other banking functionalities.",
      "techStack": ["PHP", "Laravel 8"]
    },
    {
      "id": "proj-013",
      "name": "Clubfood Co",
      "company": "PT Hashmicro",
      "description": "Developed a platform that aggregates and integrates restaurant menus, ratings, and other relevant data from multiple food delivery platforms such as GrabFood, GoFood, and Traveloka Food.",
      "techStack": ["PHP", "Laravel 8"]
    }
  ]
}
